viggoscrape.py
viggoscrape-1.2.2.dist-info/LICENSE
viggoscrape-1.2.2.dist-info/METADATA
viggoscrape-1.2.2.dist-info/WHEEL
viggoscrape-1.2.2.dist-info/top_level.txt
viggoscrape-1.2.2.dist-info/RECORD
