Metadata-Version: 2.1
Name: viggoscrape
Version: 1.2.2
Summary: Python library for scraping viggo assignments
Home-page: UNKNOWN
Author: Nangu
Author-email: nanguthenangu@gmail.com
License: UNKNOWN
Platform: UNKNOWN
Classifier: Programming Language :: Python :: 3
Classifier: License :: OSI Approved :: MIT License
Classifier: Operating System :: OS Independent
Requires-Python: >=3.6
